jdbl/__init__.py
jdbl/json_db_handle.py
jdbl/log_handle.py
jdbl/util_utils.py
jdbl-0.1.1.dist-info/LICENSE
jdbl-0.1.1.dist-info/METADATA
jdbl-0.1.1.dist-info/WHEEL
jdbl-0.1.1.dist-info/top_level.txt
jdbl-0.1.1.dist-info/RECORD
