Metadata-Version: 2.1
Name: jdbl
Version: 0.1.1
Summary: A json based database library, RAM running and including basic read-write lock.
Home-page: https://github.com/lingchuL/py-jdb
Author: lingchuL, Junyi Wang
Author-email: 2938843848@qq.com
Classifier: Programming Language :: Python :: 3
Classifier: License :: OSI Approved :: MIT License
Classifier: Operating System :: OS Independent
License-File: LICENSE
Requires-Dist: appdirs ==1.4.1
